pyea/__init__.py
pyea/differentialevolution.py
pyea/multiobjectivedifferentialevolution.py
py_ea-0.0.2.dist-info/LICENSE
py_ea-0.0.2.dist-info/METADATA
py_ea-0.0.2.dist-info/WHEEL
py_ea-0.0.2.dist-info/top_level.txt
py_ea-0.0.2.dist-info/RECORD
